csanim/Makefile
csanim/__init__.py
csanim/constants.py
csanim/consts_gen.py
csanim/draw.cpp
csanim/elements.py
csanim/interp.cpp
csanim/lib.py
csanim/libdraw.so
csanim/libinterp.so
csanim/props.py
csanim/scene.py
csanim/transition.py
csanim/utils.py
csanim/video.py
csanim/fonts/LICENSE
csanim/fonts/roboto_mono.ttf
csanim-0.0.4.dist-info/METADATA
csanim-0.0.4.dist-info/WHEEL
csanim-0.0.4.dist-info/top_level.txt
csanim-0.0.4.dist-info/RECORD
