Metadata-Version: 2.1
Name: csanim
Version: 0.0.4
Summary: A tool for creating computer science explanatory videos.
Home-page: https://github.com/phuang1024/csanim
Author: Patrick Huang
Author-email: huangpatrick16777216@gmail.com
License: UNKNOWN
Platform: UNKNOWN
Classifier: Programming Language :: Python :: 3
Classifier: License :: OSI Approved :: GNU General Public License v2 or later (GPLv2+)
Classifier: Operating System :: OS Independent
Requires-Dist: numpy
Requires-Dist: opencv-python
Requires-Dist: pillow
